McsPy/McsCMOS.py
McsPy/McsCMOSMEA.py
McsPy/McsData.py
McsPy/__init__.py
McsPy/functions_info.py
McsPy/tests/TestCMOS.py
McsPy/tests/TestCmosMeaDataStructures.py
McsPy/tests/TestRawDataStructures.py
McsPy/tests/__init__.py
McsPy/tests/TestData/README.md
McsPyDataTools-0.4.1.data/scripts/DataStreamInfo.py
McsPyDataTools-0.4.1.data/scripts/InertialAnalysis_6DoF-IMU.py
McsPyDataTools-0.4.1.data/scripts/McsPyDataTools.py
McsPyDataTools-0.4.1.data/scripts/PlotExperimentData.py
McsPyDataTools-0.4.1.dist-info/METADATA
McsPyDataTools-0.4.1.dist-info/RECORD
McsPyDataTools-0.4.1.dist-info/WHEEL
McsPyDataTools-0.4.1.dist-info/top_level.txt
McsPyDataTools-0.4.1.dist-info/zip-safe
