Metadata-Version: 1.2
Name: McsPyDataTools
Version: 0.4.1
Summary: Handling data recorded and provided by Multi Channel Systems MCS GmbH systems
Home-page: http://multichannelsystems.com
Author: J. Dietzsch, Multi Channel Systems MCS GmbH
Author-email: dietzsch@multichannelsystems.com
Maintainer: A. Walter, Multi Channel Systems MCS GmbH
Maintainer-email: walter@multichannelsystems.com
License: LICENSE.txt
Keywords: HDF5 data electrophysiology MCS
Platform: UNKNOWN
Classifier: Development Status :: 5 - Production/Stable
Classifier: Intended Audience :: Science/Research
Classifier: License :: OSI Approved :: BSD License
Classifier: Operating System :: OS Independent
Classifier: Topic :: Scientific/Engineering
Classifier: Operating System :: Unix
Classifier: Operating System :: POSIX :: Linux
Classifier: Operating System :: MacOS :: MacOS X
Classifier: Operating System :: Microsoft :: Windows
Classifier: Programming Language :: Python
Classifier: Programming Language :: Python :: 3
Classifier: Programming Language :: Python :: 3.5
Classifier: Programming Language :: Python :: 3.6
Classifier: Programming Language :: Python :: 3.7
